_phonetisaurus.cpython-312-x86_64-linux-gnu.so
sosap-0.3.0.dist-info/LICENSE
sosap-0.3.0.dist-info/WHEEL
sosap-0.3.0.dist-info/top_level.txt
sosap-0.3.0.dist-info/RECORD
sosap-0.3.0.dist-info/METADATA
openfst/lib/properties.cc
openfst/lib/symbol-table.cc
openfst/lib/fst-types.cc
openfst/lib/symbol-table-ops.cc
openfst/lib/mapped-file.cc
openfst/lib/weight.cc
openfst/lib/compat.cc
openfst/lib/util.cc
openfst/lib/flags.cc
openfst/lib/fst.cc
openfst/include/fst/properties.h
openfst/include/fst/register.h
openfst/include/fst/matcher-fst.h
openfst/include/fst/expanded-fst.h
openfst/include/fst/weight.h
openfst/include/fst/lexicographic-weight.h
openfst/include/fst/fst-decl.h
openfst/include/fst/arc-arena.h
openfst/include/fst/accumulator.h
openfst/include/fst/signed-log-weight.h
openfst/include/fst/rational.h
openfst/include/fst/pair-weight.h
openfst/include/fst/push.h
openfst/include/fst/rmfinalepsilon.h
openfst/include/fst/compact-fst.h
openfst/include/fst/relabel.h
openfst/include/fst/randequivalent.h
openfst/include/fst/reverse.h
openfst/include/fst/closure.h
openfst/include/fst/filter-state.h
openfst/include/fst/minimize.h
openfst/include/fst/test-properties.h
openfst/include/fst/add-on.h
openfst/include/fst/set-weight.h
openfst/include/fst/bi-table.h
openfst/include/fst/memory.h
openfst/include/fst/compat.h
openfst/include/fst/statesort.h
openfst/include/fst/product-weight.h
openfst/include/fst/encode.h
openfst/include/fst/replace.h
openfst/include/fst/disambiguate.h
openfst/include/fst/generic-register.h
openfst/include/fst/sparse-power-weight.h
openfst/include/fst/symbol-table-ops.h
openfst/include/fst/difference.h
openfst/include/fst/state-reachable.h
openfst/include/fst/util.h
openfst/include/fst/arcsort.h
openfst/include/fst/isomorphic.h
openfst/include/fst/project.h
openfst/include/fst/types.h
openfst/include/fst/visit.h
openfst/include/fst/arc-map.h
openfst/include/fst/compose-filter.h
openfst/include/fst/union.h
openfst/include/fst/determinize.h
openfst/include/fst/mutable-fst.h
openfst/include/fst/dfs-visit.h
openfst/include/fst/epsnormalize.h
